dbt_ibis/__init__.py
dbt_ibis/_compile.py
dbt_ibis/_dialects.py
dbt_ibis/_logging.py
dbt_ibis/_parse_dbt_project.py
dbt_ibis/_references.py
dbt_ibis/py.typed
dbt_ibis-0.11.0.dist-info/METADATA
dbt_ibis-0.11.0.dist-info/WHEEL
dbt_ibis-0.11.0.dist-info/entry_points.txt
dbt_ibis-0.11.0.dist-info/licenses/LICENSE
dbt_ibis-0.11.0.dist-info/RECORD
