Metadata-Version: 2.4
Name: dbt-ibis
Version: 0.11.0
Project-URL: Source, https://github.com/binste/dbt-ibis
Author: Stefan Binder
License-File: LICENSE
Classifier: License :: OSI Approved :: Apache Software License
Classifier: Natural Language :: English
Classifier: Programming Language :: Python :: 3.10
Classifier: Programming Language :: Python :: 3.11
Classifier: Programming Language :: Python :: 3.12
Classifier: Typing :: Typed
Requires-Python: >=3.10
Requires-Dist: click
Requires-Dist: dbt-core>=1.5
Requires-Dist: ibis-framework>=9
Provides-Extra: dev
Requires-Dist: dbt-duckdb; extra == 'dev'
Requires-Dist: hatch; extra == 'dev'
Requires-Dist: ibis-framework[duckdb]; extra == 'dev'
Requires-Dist: ipdb; extra == 'dev'
Requires-Dist: ipykernel; extra == 'dev'
Requires-Dist: ipython; extra == 'dev'
Requires-Dist: mypy; extra == 'dev'
Requires-Dist: pandas; extra == 'dev'
Requires-Dist: pytest; extra == 'dev'
Requires-Dist: pytest-mock; extra == 'dev'
Requires-Dist: ruff>=0.1.4; extra == 'dev'
Provides-Extra: doc
Requires-Dist: ghp-import; extra == 'doc'
Requires-Dist: jupyter-book; extra == 'doc'
